reactpy_jupyter.pth
reactpy_jupyter/__init__.py
reactpy_jupyter/import_resources.py
reactpy_jupyter/jupyter_server_extension.py
reactpy_jupyter/layout_widget.py
reactpy_jupyter/monkey_patch.py
reactpy_jupyter/widget_component.py
reactpy_jupyter/static/index.js
reactpy_jupyter-0.9.5.data/data/etc/jupyter/jupyter_server_config.d/reactpy-jupyter.json
reactpy_jupyter-0.9.5.dist-info/LICENSE
reactpy_jupyter-0.9.5.dist-info/METADATA
reactpy_jupyter-0.9.5.dist-info/WHEEL
reactpy_jupyter-0.9.5.dist-info/top_level.txt
reactpy_jupyter-0.9.5.dist-info/RECORD
