Metadata-Version: 2.1
Name: reactpy-jupyter
Version: 0.9.5
Summary: It's React, but in Python
Home-page: https://github.com/reactive-python/reactpy
Author: Ryan Morshead
Author-email: ryan.morshead@gmail.com
License: MIT
Keywords: interactive,widgets,DOM,React
Platform: Linux
Platform: Mac OS X
Platform: Windows
Classifier: Environment :: Web Environment
Classifier: Framework :: AsyncIO
Classifier: Framework :: Flask
Classifier: Intended Audience :: Developers
Classifier: Intended Audience :: Science/Research
Classifier: Programming Language :: Python :: 3.7
Classifier: Programming Language :: Python :: 3.8
Classifier: Programming Language :: Python :: 3.9
Classifier: Topic :: Software Development :: User Interfaces
Classifier: Topic :: Software Development :: Widget Sets
Classifier: Typing :: Typed
Requires-Python: >=3.7
License-File: LICENSE
Requires-Dist: anywidget (<1)
Requires-Dist: reactpy (>=1.0.0)
Requires-Dist: appdirs
Requires-Dist: requests
Requires-Dist: jupyter-server
Requires-Dist: notebook
Requires-Dist: typing-extensions
